{
  "AUTH0_CLIENT_ID": "<Enter the Auth0 Client Id>",
  "AUTH0_CLIENT_CERT": "<Enter the long, certificate string>",
  "AUTH0_CLIENT_AUDIENCE": "<Enter the identifier, e.g. https://mytunes/>",
  "DYNAMODB_TABLE": "<Enter a name for the metaDB table, e.g. my-tunes-tracks>",
  "USERS_TABLE": "<Enter a name for the users table, e.g. my-tunes-users>",
  "UPLOAD_BUCKET": "<Enter a name for the S3 bucket to hold the media, e.g. my-tunes-tracks>",
  "ACCESS_KEY": "<Enter the AWS IAM user Access Key>",
  "SECRET_ACCESS_KEY": "<Enter the secret key for the above user>",
  "UPLOAD_URI": "<Enter the S3 URI, e.g. https://s3.eu-west-2.amazonaws.com>"
}
